aslabs/dependencies/firestore/__init__.py
aslabs/dependencies/firestore/firestore.py
aslabs_dependencies_firestore-0.0.4.dist-info/WHEEL
aslabs_dependencies_firestore-0.0.4.dist-info/METADATA
aslabs_dependencies_firestore-0.0.4.dist-info/RECORD
