Metadata-Version: 2.1
Name: aslabs-dependencies-firestore
Version: 0.0.4
Summary: 
Author: Titusz Ban
Author-email: tituszban@antisociallabs.io
Requires-Python: >=3.9,<4.0
Classifier: Programming Language :: Python :: 3
Classifier: Programming Language :: Python :: 3.9
Classifier: Programming Language :: Python :: 3.10
Classifier: Programming Language :: Python :: 3.11
Requires-Dist: aslabs-dependencies
Requires-Dist: firebase-admin (>=5.2.0,<6.0.0)
